{"forecasts":[{"pv_estimate":0.7964,"pv_estimate10":0.7428,"pv_estimate90":0.8351,"period_end":"2025-07-14T13:30:00.0000000Z","period":"PT30M"},{"pv_estimate":0.701,"pv_estimate10":0.4117,"pv_estimate90":0.8008,"period_end":"2025-07-14T14:00:00.0000000Z","period":"PT30M"},{"pv_estimate":0.3695,"pv_estimate10":0.1141,"pv_estimate90":0.6806,"period_end":"2025-07-14T14:30:00.0000000Z","period":"PT30M"},{"pv_estimate":0.2882,"pv_estimate10":0.0897,"pv_estimate90":0.5824,"period_end":"2025-07-14T15:00:00.0000000Z","period":"PT30M"},{"pv_estimate":0.3613,"pv_estimate10":0.1162,"pv_estimate90":0.6112,"period_end":"2025-07-14T15:30:00.0000000Z","period":"PT30M"},{"pv_estimate":0.4014,"pv_estimate10":0.1358,"pv_estimate90":0.5503,"period_end":"2025-07-14T16:00:00.0000000Z","period":"PT30M"},{"pv_estimate":0.3473,"pv_estimate10":0.1401,"pv_estimate90":0.4478,"period_end":"2025-07-14T16:30:00.0000000Z","period":"PT30M"},{"pv_estimate":0.2862,"pv_estimate10":0.1221,"pv_estimate90":0.3409,"period_end":"2025-07-14T17:00:00.0000000Z","period":"PT30M"},{"pv_estimate":0.2186,"pv_estimate10":0.0977,"pv_estimate90":0.2362,"period_end":"2025-07-14T17:30:00.0000000Z","period":"PT30M"},{"pv_estimate":0.1462,"pv_estimate10":0.0693,"pv_estimate90":0.15351,"period_end":"2025-07-14T18:00:00.0000000Z","period":"PT30M"},{"pv_estimate":0.0759,"pv_estimate10":0.0404,"pv_estimate90":0.079695,"period_end":"2025-07-14T18:30:00.0000000Z","period":"PT30M"},{"pv_estimate":0.0407,"pv_estimate10":0.0215,"pv_estimate90":0.042735,"period_end":"2025-07-14T19:00:00.0000000Z","period":"PT30M"},{"pv_estimate":0.0215,"pv_estimate10":0.0095,"pv_estimate90":0.022574999999999998,"period_end":"2025-07-14T19:30:00.0000000Z","period":"PT30M"},{"pv_estimate":0.0051,"pv_estimate10":0.0017,"pv_estimate90":0.005355,"period_end":"2025-07-14T20:00:00.0000000Z","period":"PT30M"},{"pv_estimate":0,"pv_estimate10":0,"pv_estimate90":0,"period_end":"2025-07-14T20:30:00.0000000Z","period":"PT30M"},{"pv_estimate":0,"pv_estimate10":0,"pv_estimate90":0,"period_end":"2025-07-14T21:00:00.0000000Z","period":"PT30M"},{"pv_estimate":0,"pv_estimate10":0,"pv_estimate90":0,"period_end":"2025-07-14T21:30:00.0000000Z","period":"PT30M"},{"pv_estimate":0,"pv_estimate10":0,"pv_estimate90":0,"period_end":"2025-07-14T22:00:00.0000000Z","period":"PT30M"},{"pv_estimate":0,"pv_estimate10":0,"pv_estimate90":0,"period_end":"2025-07-14T22:30:00.0000000Z","period":"PT30M"},{"pv_estimate":0,"pv_estimate10":0,"pv_estimate90":0,"period_end":"2025-07-14T23:00:00.0000000Z","period":"PT30M"},{"pv_estimate":0,"pv_estimate10":0,"pv_estimate90":0,"period_end":"2025-07-14T23:30:00.0000000Z","period":"PT30M"},{"pv_estimate":0,"pv_estimate10":0,"pv_estimate90":0,"period_end":"2025-07-15T00:00:00.0000000Z","period":"PT30M"},{"pv_estimate":0,"pv_estimate10":0,"pv_estimate90":0,"period_end":"2025-07-15T00:30:00.0000000Z","period":"PT30M"},{"pv_estimate":0,"pv_estimate10":0,"pv_estimate90":0,"period_end":"2025-07-15T01:00:00.0000000Z","period":"PT30M"},{"pv_estimate":0,"pv_estimate10":0,"pv_estimate90":0,"period_end":"2025-07-15T01:30:00.0000000Z","period":"PT30M"},{"pv_estimate":0,"pv_estimate10":0,"pv_estimate90":0,"period_end":"2025-07-15T02:00:00.0000000Z","period":"PT30M"},{"pv_estimate":0,"pv_estimate10":0,"pv_estimate90":0,"period_end":"2025-07-15T02:30:00.0000000Z","period":"PT30M"},{"pv_estimate":0,"pv_estimate10":0,"pv_estimate90":0,"period_end":"2025-07-15T03:00:00.0000000Z","period":"PT30M"},{"pv_estimate":0,"pv_estimate10":0,"pv_estimate90":0,"period_end":"2025-07-15T03:30:00.0000000Z","period":"PT30M"},{"pv_estimate":0,"pv_estimate10":0,"pv_estimate90":0,"period_end":"2025-07-15T04:00:00.0000000Z","period":"PT30M"},{"pv_estimate":0,"pv_estimate10":0,"pv_estimate90":0,"period_end":"2025-07-15T04:30:00.0000000Z","period":"PT30M"},{"pv_estimate":0.0064,"pv_estimate10":0.0018,"pv_estimate90":0.007,"period_end":"2025-07-15T05:00:00.0000000Z","period":"PT30M"},{"pv_estimate":0.0261,"pv_estimate10":0.0064,"pv_estimate90":0.027405000000000002,"period_end":"2025-07-15T05:30:00.0000000Z","period":"PT30M"},{"pv_estimate":0.0535,"pv_estimate10":0.0161,"pv_estimate90":0.056175,"period_end":"2025-07-15T06:00:00.0000000Z","period":"PT30M"},{"pv_estimate":0.0842,"pv_estimate10":0.0312,"pv_estimate90":0.08841,"period_end":"2025-07-15T06:30:00.0000000Z","period":"PT30M"},{"pv_estimate":0.1564,"pv_estimate10":0.0619,"pv_estimate90":0.16422000000000003,"period_end":"2025-07-15T07:00:00.0000000Z","period":"PT30M"},{"pv_estimate":0.2421,"pv_estimate10":0.0972,"pv_estimate90":0.258,"period_end":"2025-07-15T07:30:00.0000000Z","period":"PT30M"},{"pv_estimate":0.3246,"pv_estimate10":0.1309,"pv_estimate90":0.3666,"period_end":"2025-07-15T08:00:00.0000000Z","period":"PT30M"},{"pv_estimate":0.4097,"pv_estimate10":0.1648,"pv_estimate90":0.4807,"period_end":"2025-07-15T08:30:00.0000000Z","period":"PT30M"},{"pv_estimate":0.4827,"pv_estimate10":0.1943,"pv_estimate90":0.5796,"period_end":"2025-07-15T09:00:00.0000000Z","period":"PT30M"},{"pv_estimate":0.5517,"pv_estimate10":0.2274,"pv_estimate90":0.6702,"period_end":"2025-07-15T09:30:00.0000000Z","period":"PT30M"},{"pv_estimate":0.6175,"pv_estimate10":0.2673,"pv_estimate90":0.7491,"period_end":"2025-07-15T10:00:00.0000000Z","period":"PT30M"},{"pv_estimate":0.6677,"pv_estimate10":0.2966,"pv_estimate90":0.8161,"period_end":"2025-07-15T10:30:00.0000000Z","period":"PT30M"},{"pv_estimate":0.6994,"pv_estimate10":0.3127,"pv_estimate90":0.8658,"period_end":"2025-07-15T11:00:00.0000000Z","period":"PT30M"},{"pv_estimate":0.7272,"pv_estimate10":0.338,"pv_estimate90":0.8962,"period_end":"2025-07-15T11:30:00.0000000Z","period":"PT30M"},{"pv_estimate":0.7623,"pv_estimate10":0.3784,"pv_estimate90":0.9192,"period_end":"2025-07-15T12:00:00.0000000Z","period":"PT30M"},{"pv_estimate":0.7872,"pv_estimate10":0.4116,"pv_estimate90":0.9315,"period_end":"2025-07-15T12:30:00.0000000Z","period":"PT30M"},{"pv_estimate":0.786,"pv_estimate10":0.4288,"pv_estimate90":0.9146,"period_end":"2025-07-15T13:00:00.0000000Z","period":"PT30M"},{"pv_estimate":0.7715,"pv_estimate10":0.4369,"pv_estimate90":0.8908,"period_end":"2025-07-15T13:30:00.0000000Z","period":"PT30M"},{"pv_estimate":0.7435,"pv_estimate10":0.4349,"pv_estimate90":0.8582,"period_end":"2025-07-15T14:00:00.0000000Z","period":"PT30M"},{"pv_estimate":0.7008,"pv_estimate10":0.4261,"pv_estimate90":0.8014,"period_end":"2025-07-15T14:30:00.0000000Z","period":"PT30M"},{"pv_estimate":0.6567,"pv_estimate10":0.4107,"pv_estimate90":0.7388,"period_end":"2025-07-15T15:00:00.0000000Z","period":"PT30M"},{"pv_estimate":0.5855,"pv_estimate10":0.3771,"pv_estimate90":0.6526,"period_end":"2025-07-15T15:30:00.0000000Z","period":"PT30M"},{"pv_estimate":0.5034,"pv_estimate10":0.3365,"pv_estimate90":0.561,"period_end":"2025-07-15T16:00:00.0000000Z","period":"PT30M"},{"pv_estimate":0.4154,"pv_estimate10":0.2916,"pv_estimate90":0.4584,"period_end":"2025-07-15T16:30:00.0000000Z","period":"PT30M"},{"pv_estimate":0.3195,"pv_estimate10":0.2399,"pv_estimate90":0.3446,"period_end":"2025-07-15T17:00:00.0000000Z","period":"PT30M"},{"pv_estimate":0.2235,"pv_estimate10":0.1861,"pv_estimate90":0.2318,"period_end":"2025-07-15T17:30:00.0000000Z","period":"PT30M"},{"pv_estimate":0.1335,"pv_estimate10":0.1321,"pv_estimate90":0.14017500000000002,"period_end":"2025-07-15T18:00:00.0000000Z","period":"PT30M"},{"pv_estimate":0.0562,"pv_estimate10":0.05339,"pv_estimate90":0.05901,"period_end":"2025-07-15T18:30:00.0000000Z","period":"PT30M"},{"pv_estimate":0.0393,"pv_estimate10":0.0292,"pv_estimate90":0.041265,"period_end":"2025-07-15T19:00:00.0000000Z","period":"PT30M"},{"pv_estimate":0.0216,"pv_estimate10":0.0117,"pv_estimate90":0.022680000000000002,"period_end":"2025-07-15T19:30:00.0000000Z","period":"PT30M"},{"pv_estimate":0.0045,"pv_estimate10":0.0022,"pv_estimate90":0.005,"period_end":"2025-07-15T20:00:00.0000000Z","period":"PT30M"},{"pv_estimate":0,"pv_estimate10":0,"pv_estimate90":0,"period_end":"2025-07-15T20:30:00.0000000Z","period":"PT30M"},{"pv_estimate":0,"pv_estimate10":0,"pv_estimate90":0,"period_end":"2025-07-15T21:00:00.0000000Z","period":"PT30M"},{"pv_estimate":0,"pv_estimate10":0,"pv_estimate90":0,"period_end":"2025-07-15T21:30:00.0000000Z","period":"PT30M"},{"pv_estimate":0,"pv_estimate10":0,"pv_estimate90":0,"period_end":"2025-07-15T22:00:00.0000000Z","period":"PT30M"},{"pv_estimate":0,"pv_estimate10":0,"pv_estimate90":0,"period_end":"2025-07-15T22:30:00.0000000Z","period":"PT30M"},{"pv_estimate":0,"pv_estimate10":0,"pv_estimate90":0,"period_end":"2025-07-15T23:00:00.0000000Z","period":"PT30M"},{"pv_estimate":0,"pv_estimate10":0,"pv_estimate90":0,"period_end":"2025-07-15T23:30:00.0000000Z","period":"PT30M"},{"pv_estimate":0,"pv_estimate10":0,"pv_estimate90":0,"period_end":"2025-07-16T00:00:00.0000000Z","period":"PT30M"},{"pv_estimate":0,"pv_estimate10":0,"pv_estimate90":0,"period_end":"2025-07-16T00:30:00.0000000Z","period":"PT30M"},{"pv_estimate":0,"pv_estimate10":0,"pv_estimate90":0,"period_end":"2025-07-16T01:00:00.0000000Z","period":"PT30M"},{"pv_estimate":0,"pv_estimate10":0,"pv_estimate90":0,"period_end":"2025-07-16T01:30:00.0000000Z","period":"PT30M"},{"pv_estimate":0,"pv_estimate10":0,"pv_estimate90":0,"period_end":"2025-07-16T02:00:00.0000000Z","period":"PT30M"},{"pv_estimate":0,"pv_estimate10":0,"pv_estimate90":0,"period_end":"2025-07-16T02:30:00.0000000Z","period":"PT30M"},{"pv_estimate":0,"pv_estimate10":0,"pv_estimate90":0,"period_end":"2025-07-16T03:00:00.0000000Z","period":"PT30M"},{"pv_estimate":0,"pv_estimate10":0,"pv_estimate90":0,"period_end":"2025-07-16T03:30:00.0000000Z","period":"PT30M"},{"pv_estimate":0,"pv_estimate10":0,"pv_estimate90":0,"period_end":"2025-07-16T04:00:00.0000000Z","period":"PT30M"},{"pv_estimate":0,"pv_estimate10":0,"pv_estimate90":0,"period_end":"2025-07-16T04:30:00.0000000Z","period":"PT30M"},{"pv_estimate":0.0046,"pv_estimate10":0.0011,"pv_estimate90":0.0061,"period_end":"2025-07-16T05:00:00.0000000Z","period":"PT30M"},{"pv_estimate":0.0193,"pv_estimate10":0.0045,"pv_estimate90":0.020265000000000002,"period_end":"2025-07-16T05:30:00.0000000Z","period":"PT30M"},{"pv_estimate":0.0488,"pv_estimate10":0.0112,"pv_estimate90":0.05124000000000001,"period_end":"2025-07-16T06:00:00.0000000Z","period":"PT30M"},{"pv_estimate":0.0904,"pv_estimate10":0.0245,"pv_estimate90":0.09492,"period_end":"2025-07-16T06:30:00.0000000Z","period":"PT30M"},{"pv_estimate":0.1457,"pv_estimate10":0.0578,"pv_estimate90":0.152985,"period_end":"2025-07-16T07:00:00.0000000Z","period":"PT30M"},{"pv_estimate":0.2278,"pv_estimate10":0.101,"pv_estimate90":0.2506,"period_end":"2025-07-16T07:30:00.0000000Z","period":"PT30M"},{"pv_estimate":0.3067,"pv_estimate10":0.1302,"pv_estimate90":0.3605,"period_end":"2025-07-16T08:00:00.0000000Z","period":"PT30M"},{"pv_estimate":0.3897,"pv_estimate10":0.1577,"pv_estimate90":0.4743,"period_end":"2025-07-16T08:30:00.0000000Z","period":"PT30M"},{"pv_estimate":0.4612,"pv_estimate10":0.1757,"pv_estimate90":0.5723,"period_end":"2025-07-16T09:00:00.0000000Z","period":"PT30M"},{"pv_estimate":0.5304,"pv_estimate10":0.1954,"pv_estimate90":0.6654,"period_end":"2025-07-16T09:30:00.0000000Z","period":"PT30M"},{"pv_estimate":0.5916,"pv_estimate10":0.2161,"pv_estimate90":0.7407,"period_end":"2025-07-16T10:00:00.0000000Z","period":"PT30M"},{"pv_estimate":0.6452,"pv_estimate10":0.2334,"pv_estimate90":0.8045,"period_end":"2025-07-16T10:30:00.0000000Z","period":"PT30M"},{"pv_estimate":0.6883,"pv_estimate10":0.2476,"pv_estimate90":0.8554,"period_end":"2025-07-16T11:00:00.0000000Z","period":"PT30M"},{"pv_estimate":0.7189,"pv_estimate10":0.2575,"pv_estimate90":0.8855,"period_end":"2025-07-16T11:30:00.0000000Z","period":"PT30M"},{"pv_estimate":0.7442,"pv_estimate10":0.2675,"pv_estimate90":0.9066,"period_end":"2025-07-16T12:00:00.0000000Z","period":"PT30M"},{"pv_estimate":0.7622,"pv_estimate10":0.2785,"pv_estimate90":0.9201,"period_end":"2025-07-16T12:30:00.0000000Z","period":"PT30M"},{"pv_estimate":0.7591,"pv_estimate10":0.2895,"pv_estimate90":0.9048,"period_end":"2025-07-16T13:00:00.0000000Z","period":"PT30M"},{"pv_estimate":0.7567,"pv_estimate10":0.2984,"pv_estimate90":0.8927,"period_end":"2025-07-16T13:30:00.0000000Z","period":"PT30M"}]}